arribasstools/__init__.py
arribasstools/test.py
arribasstools-0.0.2.dist-info/METADATA
arribasstools-0.0.2.dist-info/WHEEL
arribasstools-0.0.2.dist-info/top_level.txt
arribasstools-0.0.2.dist-info/RECORD
