Metadata-Version: 2.1
Name: arribasstools
Version: 0.0.2
Summary: Herramientas para facilitarte la vida
Author: Adrián Arribas
Author-email: arribas.121009@e.unavarra.es
License: UNKNOWN
Keywords: python,video,stream,video stream,camera stream,sockets
Platform: UNKNOWN
Classifier: Development Status :: 1 - Planning
Classifier: Intended Audience :: Developers
Classifier: Programming Language :: Python :: 3
Classifier: Operating System :: Unix
Classifier: Operating System :: MacOS :: MacOS X
Classifier: Operating System :: Microsoft :: Windows
